.gitignore
Dockerfile
LICENSE
MANIFEST.in
README.md
setup.cfg
setup.py
spcount/BowtieIndex.py
spcount/Taxonomy.py
spcount/__init__.py
spcount/__main__.py
spcount/__version__.py
spcount/bowtie_util.py
spcount/count_util.py
spcount/database_util.py
spcount/slurm.template
spcount.egg-info/PKG-INFO
spcount.egg-info/SOURCES.txt
spcount.egg-info/dependency_links.txt
spcount.egg-info/entry_points.txt
spcount.egg-info/not-zip-safe
spcount.egg-info/requires.txt
spcount.egg-info/top_level.txt
tests/__init__.py
tests/context.py
tests/test_count_util.py