Metadata-Version: 2.1
Name: spcount
Version: 0.0.6
Summary: Multiple genomes read count
Home-page: https://github.com/shengqh/spcount
Author: Quanhu Sheng
Author-email: quanhu.sheng.1@vumc.org
License: UNKNOWN
Download-URL: https://github.com/shengqh/spcount/archive/v0.0.6.tar.gz
Platform: UNKNOWN
Classifier: Programming Language :: Python :: 3
Classifier: License :: OSI Approved :: MIT License
Classifier: Operating System :: OS Independent
Requires-Python: >=3.6
